pytLoc/__init__.py
pytLoc/pytLoc.py
pytLoc-1.1.dist-info/LICENSE.txt
pytLoc-1.1.dist-info/METADATA
pytLoc-1.1.dist-info/WHEEL
pytLoc-1.1.dist-info/top_level.txt
pytLoc-1.1.dist-info/RECORD
