Metadata-Version: 2.1
Name: pytLoc
Version: 1.1
Summary: python tool that locks python source files using a one time pad lock. It helps to securely storing and sharing python source files.
Home-page: https://github.com/GildaRech/pytLoc
Author: Gilda Rech BANSIMBA
Author-email: bansimbagilda@gmail.com
License: UNKNOWN
Project-URL: Bug Tracker, https://github.com/GildaRech/pytLoc/issues
Platform: UNKNOWN
Classifier: Programming Language :: Python :: 3
Classifier: License :: OSI Approved :: BSD License
Classifier: Operating System :: OS Independent
Requires-Python: >=3.6
License-File: LICENSE.txt
